textbite/bite.py
textbite/geometry.py
textbite/infer.py
textbite/models/feature_extraction.py
textbite/models/improve_pagexml.py
textbite/models/utils.py
textbite/models/joiner/graph.py
textbite/models/joiner/infer.py
textbite/models/joiner/model.py
textbite/models/yolo/infer.py
textbite/visualization/visualize_bites.py
textbite-1.0.0.dist-info/LICENSE
textbite-1.0.0.dist-info/METADATA
textbite-1.0.0.dist-info/WHEEL
textbite-1.0.0.dist-info/entry_points.txt
textbite-1.0.0.dist-info/top_level.txt
textbite-1.0.0.dist-info/RECORD
