Metadata-Version: 2.1
Name: textbite
Version: 1.0.0
Summary: Toolkit for extracting logical chunks from complex document pages.
Author-email: Martin Kostelník <martinkostelnik0@gmail.com>, Karel Beneš <ibenes@fit.vutbr.cz>
License: BSD 3-Clause License
Keywords: Layout analysis,text segmentation,machine learning,language models,graph neural networks,object detection,YOLOv8
Classifier: Programming Language :: Python :: 3
Classifier: License :: OSI Approved :: BSD License
Classifier: Operating System :: OS Independent
Requires-Python: >=3.10
License-File: LICENSE
Requires-Dist: numpy
Requires-Dist: shapely
Requires-Dist: pero-ocr
Requires-Dist: ultralytics
Requires-Dist: transformers
Requires-Dist: torch-geometric
